{"address1": "2407 West 24th Street", "city": "Kearney", "state": "NE", "zip": "68845-4915", "country": "United States", "phone": "308 236 8491", "website": "https://www.buckle.com", "industry": "Apparel Retail", "industryKey": "apparel-retail", "industryDisp": "Apparel Retail", "sector": "Consumer Cyclical", "sectorKey": "consumer-cyclical", "sectorDisp": "Consumer Cyclical", "longBusinessSummary": "The Buckle, Inc. operates as a retailer of casual apparel, footwear, and accessories for young men and women in the United States. It markets a selection of brand name casual apparel, including denims, other casual bottoms, tops, sportswear, outerwear, accessories, and footwear, as well as private label merchandise primarily comprising BKE, Buckle Black, Salvage, Red by BKE, Daytrip, Gimmicks, Gilded Intent, FITZ + EDDI, Willow & Root, Outpost Makers, Departwest, Sterling & Stitch, Reclaim, BKE Vintage, Nova Industries, J.B. Holt, Modish Rebel, Maven Co-op, and Veece. The company provides services, such as hemming, gift-packaging, layaways, guest loyalty program, the Buckle private label credit card, and personalized stylist services, as well as special order system that allows stores to obtain requested merchandise from other company stores or its online order fulfillment center. The Buckle, Inc. also sells its products through its website, buckle.com. The company was formerly known as Mills Clothing, Inc. and changed its name to The Buckle, Inc. in April 1991.The Buckle, Inc. was incorporated in 1948 and is headquartered in Kearney, Nebraska.", "companyOfficers": [{"maxAge": 1, "name": "Mr. Dennis H. Nelson", "age": 74, "title": "President, CEO & Director", "yearBorn": 1950, "fiscalYear": 2023, "totalPay": 4623399, "exercisedValue": 0, "unexercisedValue": 0}, {"maxAge": 1, "name": "Mr. Thomas B. Heacock", "age": 46, "title": "Senior VP of Finance, Treasurer, CFO & Director", "yearBorn": 1978, "fiscalYear": 2023, "totalPay": 1384008, "exercisedValue": 0, "unexercisedValue": 0}, {"maxAge": 1, "name": "Mr. Brett P. Milkie", "age": 64, "title": "Senior Vice President of Leasing", "yearBorn": 1960, "fiscalYear": 2023, "totalPay": 1387485, "exercisedValue": 0, "unexercisedValue": 0}, {"maxAge": 1, "name": "Ms. Kari G. Smith", "age": 60, "title": "Executive VP of Stores & Director", "yearBorn": 1964, "fiscalYear": 2023, "totalPay": 1485930, "exercisedValue": 0, "unexercisedValue": 0}, {"maxAge": 1, "name": "Ms. Brady M. Jenschke Fritz", "age": 44, "title": "Senior VP, General Counsel & Corporate Secretary", "yearBorn": 1980, "fiscalYear": 2023, "exercisedValue": 0, "unexercisedValue": 0}, {"maxAge": 1, "name": "Ms. Michelle M. Hoffman", "age": 62, "title": "Senior Vice President of Sales", "yearBorn": 1962, "fiscalYear": 2023, "exercisedValue": 0, "unexercisedValue": 0}, {"maxAge": 1, "name": "Mr. Adam J. Akerson", "title": "VP of Finance, Controller & Assistant Treasurer", "fiscalYear": 2023, "exercisedValue": 0, "unexercisedValue": 0}], "auditRisk": 2, "boardRisk": 8, "compensationRisk": 3, "shareHolderRightsRisk": 4, "overallRisk": 5, "governanceEpochDate": 1743465600, "compensationAsOfEpochDate": 1703980800, "irWebsite": "http://www.buckle.com/corporate/investor-information", "executiveTeam": [], "maxAge": 86400, "priceHint": 2, "previousClose": 38.32, "open": 38.52, "dayLow": 37.98, "dayHigh": 38.7183, "regularMarketPreviousClose": 38.32, "regularMarketOpen": 38.52, "regularMarketDayLow": 37.98, "regularMarketDayHigh": 38.7183, "dividendRate": 1.4, "dividendYield": 3.64, "exDividendDate": 1744675200, "payoutRatio": 0.35990003, "fiveYearAvgDividendYield": 3.52, "beta": 1.109, "trailingPE": 9.876606, "forwardPE": 10.245333, "volume": 430569, "regularMarketVolume": 430569, "averageVolume": 575153, "averageVolume10days": 874250, "averageDailyVolume10Day": 874250, "bid": 35.0, "ask": 38.97, "bidSize": 8, "askSize": 8, "marketCap": 1950721664, "fiftyTwoWeekLow": 34.67, "fiftyTwoWeekHigh": 54.25, "priceToSalesTrailing12Months": 1.6019868, "fiftyDayAverage": 41.6854, "twoHundredDayAverage": 43.46075, "trailingAnnualDividendRate": 1.4, "trailingAnnualDividendYield": 0.036534447, "currency": "USD", "tradeable": false, "enterpriseValue": 1950913536, "profitMargins": 0.16052, "floatShares": 29816523, "sharesOutstanding": 50773600, "sharesShort": 2945883, "sharesShortPriorMonth": 2814153, "sharesShortPreviousMonthDate": 1739491200, "dateShortInterest": 1741910400, "sharesPercentSharesOut": 0.058000002, "heldPercentInsiders": 0.39654, "heldPercentInstitutions": 0.61074, "shortRatio": 5.54, "shortPercentOfFloat": 0.0963, "impliedSharesOutstanding": 50773600, "bookValue": 8.501, "priceToBook": 4.519468, "lastFiscalYearEnd": 1738368000, "nextFiscalYearEnd": 1769904000, "mostRecentQuarter": 1738368000, "earningsQuarterlyGrowth": -0.03, "netIncomeToCommon": 195468000, "trailingEps": 3.89, "forwardEps": 3.75, "lastSplitFactor": "10241:10000", "lastSplitDate": 1389571200, "enterpriseToRevenue": 1.602, "enterpriseToEbitda": 7.404, "52WeekChange": 0.0026096106, "SandP52WeekChange": 0.08089435, "lastDividendValue": 2.85, "lastDividendDate": 1736899200, "quoteType": "EQUITY", "currentPrice": 38.42, "targetHighPrice": 41.0, "targetLowPrice": 41.0, "targetMeanPrice": 41.0, "targetMedianPrice": 41.0, "recommendationKey": "none", "numberOfAnalystOpinions": 1, "totalCash": 290729984, "totalCashPerShare": 5.832, "ebitda": 263496000, "totalDebt": 326263008, "quickRatio": 1.391, "currentRatio": 2.053, "totalRevenue": 1217688960, "debtToEquity": 76.984, "revenuePerShare": 24.392, "returnOnAssets": 0.16734, "returnOnEquity": 0.46705002, "grossProfits": 592787008, "earningsGrowth": -0.036, "revenueGrowth": -0.008, "grossMargins": 0.48681, "ebitdaMargins": 0.21639, "operatingMargins": 0.25375998, "financialCurrency": "USD", "symbol": "BKE", "language": "en-US", "region": "US", "typeDisp": "Equity", "quoteSourceName": "Delayed Quote", "triggerable": true, "customPriceAlertConfidence": "HIGH", "shortName": "Buckle, Inc. (The)", "corporateActions": [{"header": "Dividend", "message": "BKE announced a cash dividend of 0.35 with an ex-date of Apr. 15, 2025", "meta": {"eventType": "DIVIDEND", "dateEpochMs": 1744689600000, "amount": "0.35"}}], "preMarketTime": 1743596894, "regularMarketTime": 1743537602, "exchange": "NYQ", "messageBoardId": "finmb_318463", "exchangeTimezoneName": "America/New_York", "exchangeTimezoneShortName": "EDT", "gmtOffSetMilliseconds": -14400000, "market": "us_market", "esgPopulated": false, "fiftyDayAverageChange": -3.2654, "fiftyDayAverageChangePercent": -0.07833438, "twoHundredDayAverageChange": -5.0407524, "twoHundredDayAverageChangePercent": -0.115984015, "sourceInterval": 15, "exchangeDataDelayedBy": 0, "cryptoTradeable": false, "marketState": "PRE", "hasPrePostMarketData": true, "firstTradeDateMilliseconds": 705331800000, "preMarketChange": -0.3199997, "preMarketChangePercent": -0.8328988, "preMarketPrice": 38.1, "regularMarketChange": 0.0999985, "regularMarketDayRange": "37.98 - 38.7183", "fullExchangeName": "NYSE", "averageDailyVolume3Month": 575153, "fiftyTwoWeekLowChange": 3.75, "fiftyTwoWeekLowChangePercent": 0.10816268, "fiftyTwoWeekRange": "34.67 - 54.25", "fiftyTwoWeekHighChange": -15.830002, "fiftyTwoWeekHighChangePercent": -0.29179728, "fiftyTwoWeekChangePercent": 0.26096106, "dividendDate": 1745884800, "earningsTimestamp": 1741949400, "earningsTimestampStart": 1747917000, "earningsTimestampEnd": 1748262600, "earningsCallTimestampStart": 1741960800, "earningsCallTimestampEnd": 1741960800, "isEarningsDateEstimate": true, "epsTrailingTwelveMonths": 3.89, "epsForward": 3.75, "epsCurrentYear": 3.72202, "priceEpsCurrentYear": 10.322351, "longName": "The Buckle, Inc.", "regularMarketChangePercent": 0.260956, "regularMarketPrice": 38.42, "displayName": "The Buckle", "trailingPegRatio": null}