{"address1": "275 Broadhollow Road", "city": "Melville", "state": "NY", "zip": "11747", "country": "United States", "phone": "516 671 4900", "fax": "516 454 8601", "website": "https://www.fnbli.com", "industry": "Banks - Regional", "industryKey": "banks-regional", "industryDisp": "Banks - Regional", "sector": "Financial Services", "sectorKey": "financial-services", "sectorDisp": "Financial Services", "longBusinessSummary": "The First of Long Island Corporation operates as a bank holding company for The First National Bank of Long Island that provides financial services to small and medium market businesses, professional service firms, not-for-profits, municipalities, and consumers in the United States. The company offers business and personal checking products; negotiable order of withdrawal, interest on lawyer, escrow service, rent security, personal and nonpersonal money market and savings, and individual retirement accounts; and time deposits. It also provides commercial and residential mortgage, commercial and industrial, small business, multifamily, owner-occupied, municipal, Small Business Administration, construction and land development, consumer, and revolving home equity lines of credit/loans, as well as standby letters of credit; and debit and credit cards. In addition, the company offers life insurance; investment management, trust, estate, and custody; retail investment; overdraft, bill payment, lockbox, and ACH; safe deposit box rental, wire transfer, money order, checkbook printing, check, and ATM; and online and mobile banking services. The First of Long Island Corporation was founded in 1927 and is headquartered in Melville, New York.", "fullTimeEmployees": 265, "companyOfficers": [{"maxAge": 1, "name": "Mr. Christopher D. Becker", "age": 58, "title": "President, CEO & Director", "yearBorn": 1966, "fiscalYear": 2024, "totalPay": 818285, "exercisedValue": 0, "unexercisedValue": 0}, {"maxAge": 1, "name": "Ms. Janet T. Verneuille CPA", "age": 63, "title": "Senior Executive VP, CFO & Treasurer", "yearBorn": 1961, "fiscalYear": 2024, "totalPay": 486406, "exercisedValue": 0, "unexercisedValue": 0}, {"maxAge": 1, "name": "Mr. Christopher J. Hilton DL, FCIArb, MA (Cantab)", "age": 47, "title": "Senior Executive Vice President", "yearBorn": 1977, "fiscalYear": 2024, "totalPay": 463400, "exercisedValue": 0, "unexercisedValue": 0}, {"maxAge": 1, "name": "Mr. Michael J. Spolarich", "age": 55, "title": "Executive Vice President", "yearBorn": 1969, "fiscalYear": 2024, "totalPay": 444105, "exercisedValue": 0, "unexercisedValue": 0}, {"maxAge": 1, "name": "Ms. Susanne  Pheffer", "age": 61, "title": "Executive Vice President", "yearBorn": 1963, "fiscalYear": 2024, "totalPay": 450422, "exercisedValue": 0, "unexercisedValue": 0}, {"maxAge": 1, "name": "Shannon  Shakespeare", "title": "Senior VP & Chief Human Resources Officer", "fiscalYear": 2024, "exercisedValue": 0, "unexercisedValue": 0}, {"maxAge": 1, "name": "Mr. Richard P. Perro", "age": 58, "title": "Executive Vice President", "yearBorn": 1966, "fiscalYear": 2024, "totalPay": 336208, "exercisedValue": 2423, "unexercisedValue": 0}, {"maxAge": 1, "name": "Robert J. Colosa", "title": "Senior VP & Chief Auditor", "fiscalYear": 2024, "exercisedValue": 0, "unexercisedValue": 0}, {"maxAge": 1, "name": "Ms. Maria E. Doyle CPA", "title": "Senior VP and Director of Financial Reporting & Controls", "fiscalYear": 2024, "exercisedValue": 0, "unexercisedValue": 0}, {"maxAge": 1, "name": "Mr. Tanweer S. Ansari Esq.", "age": 49, "title": "Executive VP & Chief Risk Officer", "yearBorn": 1975, "fiscalYear": 2024, "exercisedValue": 0, "unexercisedValue": 0}], "auditRisk": 3, "boardRisk": 2, "compensationRisk": 3, "shareHolderRightsRisk": 7, "overallRisk": 4, "governanceEpochDate": 1743465600, "compensationAsOfEpochDate": 1735603200, "executiveTeam": [], "maxAge": 86400, "priceHint": 2, "previousClose": 12.35, "open": 12.6, "dayLow": 12.222, "dayHigh": 12.6, "regularMarketPreviousClose": 12.35, "regularMarketOpen": 12.6, "regularMarketDayLow": 12.222, "regularMarketDayHigh": 12.6, "dividendRate": 0.84, "dividendYield": 6.82, "exDividendDate": 1742774400, "payoutRatio": 1.12, "fiveYearAvgDividendYield": 5.37, "beta": 0.749, "trailingPE": 16.413334, "forwardPE": 10.258333, "volume": 81235, "regularMarketVolume": 81235, "averageVolume": 86220, "averageVolume10days": 98560, "averageDailyVolume10Day": 98560, "bid": 12.27, "ask": 12.37, "bidSize": 1, "askSize": 1, "marketCap": 278640544, "fiftyTwoWeekLow": 9.3, "fiftyTwoWeekHigh": 15.03, "priceToSalesTrailing12Months": 3.280903, "fiftyDayAverage": 12.6754, "twoHundredDayAverage": 12.51325, "trailingAnnualDividendRate": 0.84, "trailingAnnualDividendYield": 0.068016194, "currency": "USD", "tradeable": false, "enterpriseValue": 697274944, "profitMargins": 0.20106001, "floatShares": 21380657, "sharesOutstanding": 22635300, "sharesShort": 135198, "sharesShortPriorMonth": 89376, "sharesShortPreviousMonthDate": 1739491200, "dateShortInterest": 1741910400, "sharesPercentSharesOut": 0.006, "heldPercentInsiders": 0.056739997, "heldPercentInstitutions": 0.57368, "shortRatio": 1.94, "shortPercentOfFloat": 0.0072000003, "impliedSharesOutstanding": 22635300, "bookValue": 16.767, "priceToBook": 0.7341803, "lastFiscalYearEnd": 1735603200, "nextFiscalYearEnd": 1767139200, "mostRecentQuarter": 1735603200, "earningsQuarterlyGrowth": -0.465, "netIncomeToCommon": 17076000, "trailingEps": 0.75, "forwardEps": 1.2, "lastSplitFactor": "3:2", "lastSplitDate": 1480377600, "enterpriseToRevenue": 8.21, "52WeekChange": 0.16351604, "SandP52WeekChange": 0.08089435, "lastDividendValue": 0.21, "lastDividendDate": 1742774400, "quoteType": "EQUITY", "currentPrice": 12.31, "targetHighPrice": 16.56, "targetLowPrice": 16.56, "targetMeanPrice": 16.56, "targetMedianPrice": 16.56, "recommendationMean": 2.0, "recommendationKey": "buy", "numberOfAnalystOpinions": 1, "totalCash": 38725000, "totalCashPerShare": 1.711, "totalDebt": 457359008, "totalRevenue": 84928000, "revenuePerShare": 3.77, "returnOnAssets": 0.00409, "returnOnEquity": 0.045, "grossProfits": 84928000, "operatingCashflow": 14950000, "earningsGrowth": -0.477, "revenueGrowth": 0.008, "grossMargins": 0.0, "ebitdaMargins": 0.0, "operatingMargins": 0.21509, "financialCurrency": "USD", "symbol": "FLIC", "language": "en-US", "region": "US", "typeDisp": "Equity", "quoteSourceName": "Nasdaq Real Time Price", "triggerable": true, "customPriceAlertConfidence": "HIGH", "shortName": "The First of Long Island Corpor", "longName": "The First of Long Island Corporation", "preMarketChange": 0.029999733, "preMarketChangePercent": 0.24370213, "preMarketPrice": 12.34, "regularMarketChange": -0.03999996, "regularMarketDayRange": "12.222 - 12.6", "fullExchangeName": "NasdaqCM", "averageDailyVolume3Month": 86220, "fiftyTwoWeekLowChange": 3.0100002, "fiftyTwoWeekLowChangePercent": 0.32365593, "fiftyTwoWeekRange": "9.3 - 15.03", "fiftyTwoWeekHighChange": -2.7199993, "fiftyTwoWeekHighChangePercent": -0.18097135, "fiftyTwoWeekChangePercent": 16.351604, "dividendDate": 1743638400, "earningsTimestamp": 1738274400, "earningsTimestampStart": 1745438400, "earningsTimestampEnd": 1745870400, "earningsCallTimestampStart": 1722016800, "earningsCallTimestampEnd": 1722016800, "isEarningsDateEstimate": true, "epsTrailingTwelveMonths": 0.75, "epsForward": 1.2, "epsCurrentYear": 1.25, "priceEpsCurrentYear": 9.848001, "fiftyDayAverageChange": -0.36539936, "fiftyDayAverageChangePercent": -0.028827442, "twoHundredDayAverageChange": -0.20324993, "twoHundredDayAverageChangePercent": -0.016242776, "sourceInterval": 15, "exchangeDataDelayedBy": 0, "averageAnalystRating": "2.0 - Buy", "cryptoTradeable": false, "hasPrePostMarketData": true, "firstTradeDateMilliseconds": 537460200000, "regularMarketChangePercent": -0.32388633, "regularMarketPrice": 12.31, "corporateActions": [], "preMarketTime": 1743582255, "regularMarketTime": 1743537602, "exchange": "NCM", "messageBoardId": "finmb_272192", "exchangeTimezoneName": "America/New_York", "exchangeTimezoneShortName": "EDT", "gmtOffSetMilliseconds": -14400000, "market": "us_market", "esgPopulated": false, "marketState": "PRE", "displayName": "The First of Long Island", "trailingPegRatio": null}