{"address1": "1373 Boggs Drive", "city": "Mount Airy", "state": "NC", "zip": "27030", "country": "United States", "phone": "336 786 2141", "fax": "336 786 2144", "website": "https://www.insteel.com", "industry": "Metal Fabrication", "industryKey": "metal-fabrication", "industryDisp": "Metal Fabrication", "sector": "Industrials", "sectorKey": "industrials", "sectorDisp": "Industrials", "longBusinessSummary": "Insteel Industries, Inc., together with its subsidiaries, manufactures and markets steel wire reinforcing products for concrete construction applications. The company offers prestressed concrete strand (PC strand) and welded wire reinforcement (WWR) products. Its PC strand is a seven-wire strand that is used to impart compression forces into precast concrete elements and structures providing reinforcement for bridges, parking decks, buildings, and other concrete structures. The company's WWR engineered reinforcing product is used in nonresidential and residential construction. It produces a range of WWR products, such as engineered structural mesh, an engineered made-to-order product that is used as the primary reinforcement for concrete elements or structures serving as a reinforcing solution for hot-rolled rebar; concrete pipe reinforcement, an engineered made-to-order product, which is used as the primary reinforcement in concrete pipe, box culverts, and precast manholes for drainage and sewage systems, water treatment facilities, and other related applications; and standard welded wire reinforcement, a secondary reinforcing product for crack control applications in residential and light nonresidential construction, including driveways, sidewalks, and various slab-on-grade applications. It sells its products through sales representatives to the manufacturers of concrete products, rebar fabricators, distributors, and contractors. The company was founded in 1953 and is headquartered in Mount Airy, North Carolina.", "fullTimeEmployees": 929, "companyOfficers": [{"maxAge": 1, "name": "Mr. Howard Osler Woltz III", "age": 68, "title": "President, CEO & Chairman", "yearBorn": 1956, "fiscalYear": 2024, "totalPay": 1013952, "exercisedValue": 0, "unexercisedValue": 596199}, {"maxAge": 1, "name": "Mr. Scot R. Jafroodi", "age": 54, "title": "VP, CFO & Treasurer", "yearBorn": 1970, "fiscalYear": 2024, "totalPay": 398308, "exercisedValue": 32473, "unexercisedValue": 172137}, {"maxAge": 1, "name": "Mr. Richard T. Wagner", "age": 65, "title": "Senior VP & COO", "yearBorn": 1959, "fiscalYear": 2024, "totalPay": 484447, "exercisedValue": 0, "unexercisedValue": 32283}, {"maxAge": 1, "name": "Ms. Elizabeth Carroll Southern", "age": 42, "title": "VP of Administration, Secretary & Chief Legal Officer", "yearBorn": 1982, "fiscalYear": 2024, "totalPay": 343346, "exercisedValue": 0, "unexercisedValue": 0}, {"maxAge": 1, "name": "Mr. James R. York", "age": 65, "title": "Senior Vice President of Sourcing & Logistics", "yearBorn": 1959, "fiscalYear": 2024, "totalPay": 351370, "exercisedValue": 0, "unexercisedValue": 156436}], "auditRisk": 7, "boardRisk": 7, "compensationRisk": 5, "shareHolderRightsRisk": 7, "overallRisk": 6, "governanceEpochDate": 1743465600, "compensationAsOfEpochDate": 1735603200, "executiveTeam": [], "maxAge": 86400, "priceHint": 2, "previousClose": 26.3, "open": 26.0, "dayLow": 25.975, "dayHigh": 26.52, "regularMarketPreviousClose": 26.3, "regularMarketOpen": 26.0, "regularMarketDayLow": 25.975, "regularMarketDayHigh": 26.52, "dividendRate": 0.12, "dividendYield": 0.46, "exDividendDate": 1741910400, "payoutRatio": 0.121199995, "fiveYearAvgDividendYield": 0.41, "beta": 1.091, "trailingPE": 26.616161, "forwardPE": 9.377225, "volume": 82155, "regularMarketVolume": 82155, "averageVolume": 173925, "averageVolume10days": 173760, "averageDailyVolume10Day": 173760, "bid": 10.45, "ask": 26.42, "bidSize": 8, "askSize": 8, "marketCap": 511996320, "fiftyTwoWeekLow": 23.6, "fiftyTwoWeekHigh": 37.55, "priceToSalesTrailing12Months": 0.9530956, "fiftyDayAverage": 28.259, "twoHundredDayAverage": 29.70215, "trailingAnnualDividendRate": 0.12, "trailingAnnualDividendYield": 0.004562738, "currency": "USD", "tradeable": false, "enterpriseValue": 478359168, "profitMargins": 0.03584, "floatShares": 18522250, "sharesOutstanding": 19430600, "sharesShort": 780088, "sharesShortPriorMonth": 711836, "sharesShortPreviousMonthDate": 1739491200, "dateShortInterest": 1741910400, "sharesPercentSharesOut": 0.0401, "heldPercentInsiders": 0.04934, "heldPercentInstitutions": 0.85769, "shortRatio": 5.17, "shortPercentOfFloat": 0.051799998, "impliedSharesOutstanding": 19430600, "bookValue": 17.068, "priceToBook": 1.5438247, "lastFiscalYearEnd": 1727481600, "nextFiscalYearEnd": 1759017600, "mostRecentQuarter": 1735344000, "earningsQuarterlyGrowth": -0.045, "netIncomeToCommon": 19254000, "trailingEps": 0.99, "forwardEps": 2.81, "lastSplitFactor": "2:1", "lastSplitDate": 1150675200, "enterpriseToRevenue": 0.89, "enterpriseToEbitda": 12.617, "52WeekChange": -0.28279805, "SandP52WeekChange": 0.08089435, "lastDividendValue": 0.03, "lastDividendDate": 1741910400, "quoteType": "EQUITY", "currentPrice": 26.35, "targetHighPrice": 39.0, "targetLowPrice": 39.0, "targetMeanPrice": 39.0, "targetMedianPrice": 39.0, "recommendationKey": "none", "numberOfAnalystOpinions": 1, "totalCash": 35951000, "totalCashPerShare": 1.85, "ebitda": 37913000, "totalDebt": 2313000, "quickRatio": 1.852, "currentRatio": 4.088, "totalRevenue": 537193024, "debtToEquity": 0.697, "revenuePerShare": 27.546, "returnOnAssets": 0.03423, "returnOnEquity": 0.05789, "grossProfits": 52891000, "freeCashflow": 26532876, "operatingCashflow": 55356000, "earningsGrowth": -0.045, "revenueGrowth": 0.066, "grossMargins": 0.09846, "ebitdaMargins": 0.07058, "operatingMargins": 0.0126600005, "financialCurrency": "USD", "symbol": "IIIN", "language": "en-US", "region": "US", "typeDisp": "Equity", "quoteSourceName": "Delayed Quote", "triggerable": true, "customPriceAlertConfidence": "HIGH", "hasPrePostMarketData": true, "firstTradeDateMilliseconds": 700842600000, "preMarketChange": -0.09000015, "preMarketChangePercent": -0.34155655, "preMarketPrice": 26.26, "regularMarketChange": 0.0500011, "regularMarketDayRange": "25.975 - 26.52", "fullExchangeName": "NYSE", "averageDailyVolume3Month": 173925, "fiftyTwoWeekLowChange": 2.75, "fiftyTwoWeekLowChangePercent": 0.11652542, "fiftyTwoWeekRange": "23.6 - 37.55", "fiftyTwoWeekHighChange": -11.199999, "fiftyTwoWeekHighChangePercent": -0.29826894, "fiftyTwoWeekChangePercent": -28.279804, "dividendDate": 1743120000, "earningsTimestamp": 1744893000, "earningsTimestampStart": 1744893000, "earningsTimestampEnd": 1744893000, "earningsCallTimestampStart": 1744898400, "earningsCallTimestampEnd": 1744898400, "isEarningsDateEstimate": false, "epsTrailingTwelveMonths": 0.99, "epsForward": 2.81, "epsCurrentYear": 1.39, "priceEpsCurrentYear": 18.956835, "fiftyDayAverageChange": -1.9090004, "fiftyDayAverageChangePercent": -0.067553714, "twoHundredDayAverageChange": -3.35215, "twoHundredDayAverageChangePercent": -0.11285883, "shortName": "Insteel Industries, Inc.", "longName": "Insteel Industries, Inc.", "regularMarketChangePercent": 0.190118, "regularMarketPrice": 26.35, "marketState": "PRE", "corporateActions": [], "preMarketTime": 1743598040, "regularMarketTime": 1743537602, "exchange": "NYQ", "messageBoardId": "finmb_281083", "exchangeTimezoneName": "America/New_York", "exchangeTimezoneShortName": "EDT", "gmtOffSetMilliseconds": -14400000, "market": "us_market", "esgPopulated": false, "sourceInterval": 15, "exchangeDataDelayedBy": 0, "cryptoTradeable": false, "displayName": "Insteel Industries", "trailingPegRatio": 1.7567}