{"address1": "10089 Fairfax Boulevard", "city": "Fairfax", "state": "VA", "zip": "22030", "country": "United States", "phone": "703 481 4567", "website": "https://mstreetbank.com", "industry": "Banks - Regional", "industryKey": "banks-regional", "industryDisp": "Banks - Regional", "sector": "Financial Services", "sectorKey": "financial-services", "sectorDisp": "Financial Services", "longBusinessSummary": "MainStreet Bancshares, Inc. operates as the bank holding company for MainStreet Bank that provides various banking products and services for individuals, small to medium-sized businesses, and professional service organizations. The company offers demand, NOW, money market, savings, and sweep accounts, as well as certificates of deposit; business and consumer checking, interest-bearing checking, business account analysis, and other depository services; and cash management, wire transfer, check imaging, bill pay, remote deposit capture, and courier services. It also provides commercial loans, include government contract receivables, plant and equipment, general working capital, contract administration, and acquisition loans; commercial real estate, real estate construction, and residential real estate loans; and consumer loans comprising term loans and overdraft protection, as well as debit and credit cards. In addition, the company offers deposit insurance solutions; remote deposit of checks; and internet bill payment, online cash management, and online and mobile banking services. It operates in Herndon, Fairfax, McLean, Leesburg, Clarendon, and Washington D.C., as well as automated teller machines. The company was incorporated in 2003 and is headquartered in Fairfax, Virginia.", "fullTimeEmployees": 204, "companyOfficers": [{"maxAge": 1, "name": "Mr. Jeff W. Dick", "age": 63, "title": "CEO & Chairman of the Board", "yearBorn": 1961, "fiscalYear": 2023, "totalPay": 1138901, "exercisedValue": 0, "unexercisedValue": 0}, {"maxAge": 1, "name": "Mr. Thomas J. Chmelik", "age": 61, "title": "Senior EVP, CFO, Corporate Secretary & Director", "yearBorn": 1963, "fiscalYear": 2023, "totalPay": 382387, "exercisedValue": 0, "unexercisedValue": 0}, {"maxAge": 1, "name": "Mr. Abdulhamid  Hersiburane", "age": 62, "title": "President & Director of MainStreet Bank", "yearBorn": 1962, "fiscalYear": 2023, "totalPay": 544190, "exercisedValue": 0, "unexercisedValue": 0}, {"maxAge": 1, "name": "Mr. Todd  Youngren", "title": "President", "fiscalYear": 2023, "exercisedValue": 0, "unexercisedValue": 0}, {"maxAge": 1, "name": "Mr. Richard Alexander Vari", "age": 35, "title": "Senior VP & Chief Accounting Officer", "yearBorn": 1989, "fiscalYear": 2023, "exercisedValue": 0, "unexercisedValue": 0}, {"maxAge": 1, "name": "Mr. Jacob  Hutchinson", "title": "Executive VP & Chief Information Officer", "fiscalYear": 2023, "exercisedValue": 0, "unexercisedValue": 0}, {"maxAge": 1, "name": "Ms. Trish  Smith", "title": "Executive VP & Chief Human Resources Officer", "fiscalYear": 2023, "exercisedValue": 0, "unexercisedValue": 0}, {"maxAge": 1, "name": "Mr. Tom  Floyd", "title": "Executive Vice President", "fiscalYear": 2023, "exercisedValue": 0, "unexercisedValue": 0}, {"maxAge": 1, "name": "William  Freesmeier", "title": "Senior Vice President", "fiscalYear": 2023, "exercisedValue": 0, "unexercisedValue": 0}, {"maxAge": 1, "name": "Michael B. Baboval", "title": "Chief Risk Officer", "fiscalYear": 2023, "exercisedValue": 0, "unexercisedValue": 0}], "compensationAsOfEpochDate": 1703980800, "executiveTeam": [], "maxAge": 86400, "priceHint": 2, "previousClose": 24.85, "open": 24.72, "dayLow": 24.6, "dayHigh": 24.728, "regularMarketPreviousClose": 24.85, "regularMarketOpen": 24.72, "regularMarketDayLow": 24.6, "regularMarketDayHigh": 24.728, "dividendRate": 1.88, "dividendYield": 7.6, "exDividendDate": 1741910400, "beta": 0.548, "trailingPE": 9.365439, "volume": 6300, "regularMarketVolume": 6300, "averageVolume": 1320, "averageVolume10days": 1600, "averageDailyVolume10Day": 1600, "bid": 0.0, "ask": 0.0, "bidSize": 0, "askSize": 0, "fiftyTwoWeekLow": 21.05, "fiftyTwoWeekHigh": 25.27, "fiftyDayAverage": 24.53906, "twoHundredDayAverage": 23.583105, "trailingAnnualDividendRate": 0.4, "trailingAnnualDividendYield": 0.016096579, "currency": "USD", "tradeable": false, "enterpriseValue": 83775000, "profitMargins": -0.16896999, "floatShares": 6061672, "sharesShort": 4832, "sharesShortPriorMonth": 2706, "sharesShortPreviousMonthDate": 1739491200, "dateShortInterest": 1741910400, "shortRatio": 2.94, "bookValue": 24.535, "priceToBook": 1.0050622, "lastFiscalYearEnd": 1735603200, "nextFiscalYearEnd": 1767139200, "mostRecentQuarter": 1735603200, "netIncomeToCommon": -12136000, "trailingEps": 2.633, "enterpriseToRevenue": 1.418, "52WeekChange": 0.07213044, "SandP52WeekChange": 0.08089435, "lastDividendValue": 0.469, "lastDividendDate": 1741910400, "quoteType": "EQUITY", "currentPrice": 24.6592, "recommendationKey": "none", "totalCash": 229423008, "totalCashPerShare": 30.629, "totalDebt": 101228000, "totalRevenue": 59063000, "revenuePerShare": 7.765, "returnOnAssets": -0.00468, "returnOnEquity": -0.046469998, "grossProfits": 59063000, "operatingCashflow": 14740000, "revenueGrowth": -0.237, "grossMargins": 0.0, "ebitdaMargins": 0.0, "operatingMargins": 0.0053600003, "financialCurrency": "USD", "symbol": "MNSBP", "language": "en-US", "region": "US", "typeDisp": "Equity", "quoteSourceName": "Nasdaq Real Time Price", "triggerable": true, "customPriceAlertConfidence": "HIGH", "regularMarketChangePercent": -0.76780564, "regularMarketPrice": 24.6592, "marketState": "PRE", "shortName": "MainStreet Bancshares, Inc. - D", "longName": "MainStreet Bancshares, Inc.", "fiftyDayAverageChange": 0.120140076, "fiftyDayAverageChangePercent": 0.004895871, "twoHundredDayAverageChange": 1.0760956, "twoHundredDayAverageChangePercent": 0.045629937, "sourceInterval": 15, "exchangeDataDelayedBy": 0, "cryptoTradeable": false, "hasPrePostMarketData": true, "firstTradeDateMilliseconds": 1600263000000, "regularMarketChange": -0.19079971, "regularMarketDayRange": "24.6 - 24.728", "fullExchangeName": "NasdaqCM", "averageDailyVolume3Month": 1320, "fiftyTwoWeekLowChange": 3.6092014, "fiftyTwoWeekLowChangePercent": 0.17145851, "fiftyTwoWeekRange": "21.05 - 25.27", "fiftyTwoWeekHighChange": -0.6107998, "fiftyTwoWeekHighChangePercent": -0.024170944, "fiftyTwoWeekChangePercent": 7.213044, "dividendDate": 1743292800, "earningsTimestamp": 1737983917, "earningsTimestampStart": 1745238600, "earningsTimestampEnd": 1745584200, "earningsCallTimestampStart": 1738004400, "earningsCallTimestampEnd": 1738004400, "isEarningsDateEstimate": true, "epsTrailingTwelveMonths": 2.633, "corporateActions": [], "regularMarketTime": 1743537600, "exchange": "NCM", "messageBoardId": "finmb_23732745", "exchangeTimezoneName": "America/New_York", "exchangeTimezoneShortName": "EDT", "gmtOffSetMilliseconds": -14400000, "market": "us_market", "esgPopulated": false, "displayName": "MainStreet Bancshares", "trailingPegRatio": null}