{"address1": "601 E. Beardsley Ave.", "city": "Elkhart", "state": "IN", "zip": "46514-3305", "country": "United States", "phone": "574 970 7460", "website": "https://www.thorindustries.com", "industry": "Recreational Vehicles", "industryKey": "recreational-vehicles", "industryDisp": "Recreational Vehicles", "sector": "Consumer Cyclical", "sectorKey": "consumer-cyclical", "sectorDisp": "Consumer Cyclical", "longBusinessSummary": "THOR Industries, Inc. designs, manufactures, and sells recreational vehicles (RVs), and related parts and accessories in the United States, Germany, Canada, rest of Europe, and internationally. The company offers travel trailers; gasoline and diesel Class A, Class B, and Class C motorhomes; conventional travel trailers and fifth wheels; luxury fifth wheels; and motorcaravans, caravans, campervans, and urban vehicles. It also provides aluminum extrusion and specialized component products to RV and other manufacturers. The company provides its products through independent and non-franchise dealers. THOR Industries, Inc. was founded in 1980 and is based in Elkhart, Indiana.", "fullTimeEmployees": 22300, "companyOfficers": [{"maxAge": 1, "name": "Mr. Robert W. Martin", "age": 55, "title": "President, CEO & Director", "yearBorn": 1969, "fiscalYear": 2024, "totalPay": 4916902, "exercisedValue": 0, "unexercisedValue": 0}, {"maxAge": 1, "name": "Mr. Peter B. Orthwein", "age": 79, "title": "Co-Founder & Chairman Emeritus", "yearBorn": 1945, "fiscalYear": 2024, "totalPay": 170000, "exercisedValue": 0, "unexercisedValue": 0}, {"maxAge": 1, "name": "Ms. Colleen A. Zuhl CPA", "age": 58, "title": "Senior VP & CFO", "yearBorn": 1966, "fiscalYear": 2024, "totalPay": 2269578, "exercisedValue": 0, "unexercisedValue": 0}, {"maxAge": 1, "name": "Mr. W. Todd Woelfer", "age": 57, "title": "Senior VP & COO", "yearBorn": 1967, "fiscalYear": 2024, "totalPay": 2241060, "exercisedValue": 0, "unexercisedValue": 0}, {"maxAge": 1, "name": "Mr. Trevor Q. Gasper J.D.", "age": 43, "title": "Senior VP, General Counsel & Secretary", "yearBorn": 1981, "fiscalYear": 2024, "totalPay": 1159383, "exercisedValue": 0, "unexercisedValue": 0}, {"maxAge": 1, "name": "Ms. Michele L. McDermott", "age": 53, "title": "Senior VP & CHRO", "yearBorn": 1971, "fiscalYear": 2024, "totalPay": 538273, "exercisedValue": 0, "unexercisedValue": 0}, {"maxAge": 1, "name": "Ms. Renee  Jones", "title": "Vice President of Marketing", "fiscalYear": 2024, "totalPay": 190000, "exercisedValue": 0, "unexercisedValue": 0}, {"maxAge": 1, "name": "Mr. Troy  James", "title": "Senior Vice President of International Operations", "fiscalYear": 2024, "exercisedValue": 0, "unexercisedValue": 0}, {"maxAge": 1, "name": "Mr. McKay  Featherstone", "title": "Senior Vice President of Global Innovation", "fiscalYear": 2024, "exercisedValue": 0, "unexercisedValue": 0}, {"maxAge": 1, "name": "Mr. Ryan  Juday", "title": "President of KZ Recreational Vehicles", "fiscalYear": 2024, "exercisedValue": 0, "unexercisedValue": 0}], "auditRisk": 2, "boardRisk": 1, "compensationRisk": 3, "shareHolderRightsRisk": 2, "overallRisk": 1, "governanceEpochDate": 1743465600, "compensationAsOfEpochDate": 1735603200, "irWebsite": "http://www.thorindustries.com/", "executiveTeam": [], "maxAge": 86400, "priceHint": 2, "previousClose": 75.81, "open": 75.5, "dayLow": 74.95, "dayHigh": 77.1559, "regularMarketPreviousClose": 75.81, "regularMarketOpen": 75.5, "regularMarketDayLow": 74.95, "regularMarketDayHigh": 77.1559, "dividendRate": 2.0, "dividendYield": 2.61, "exDividendDate": 1744070400, "payoutRatio": 0.5199, "fiveYearAvgDividendYield": 1.82, "beta": 1.736, "trailingPE": 20.323608, "forwardPE": 11.860682, "volume": 644851, "regularMarketVolume": 644851, "averageVolume": 812288, "averageVolume10days": 879370, "averageDailyVolume10Day": 879370, "bid": 75.09, "ask": 78.15, "bidSize": 8, "askSize": 9, "marketCap": 4076460032, "fiftyTwoWeekLow": 74.95, "fiftyTwoWeekHigh": 118.85, "priceToSalesTrailing12Months": 0.4292741, "fiftyDayAverage": 93.0, "twoHundredDayAverage": 100.30425, "trailingAnnualDividendRate": 1.96, "trailingAnnualDividendYield": 0.02585411, "currency": "USD", "tradeable": false, "enterpriseValue": 4778172416, "profitMargins": 0.021289999, "floatShares": 50746095, "sharesOutstanding": 53203600, "sharesShort": 4217150, "sharesShortPriorMonth": 3796559, "sharesShortPreviousMonthDate": 1739491200, "dateShortInterest": 1741910400, "sharesPercentSharesOut": 0.0793, "heldPercentInsiders": 0.04539, "heldPercentInstitutions": 1.0193, "shortRatio": 3.9, "shortPercentOfFloat": 0.0928, "impliedSharesOutstanding": 54094900, "bookValue": 74.277, "priceToBook": 1.0315441, "lastFiscalYearEnd": 1722384000, "nextFiscalYearEnd": 1753920000, "mostRecentQuarter": 1738281600, "netIncomeToCommon": 202143008, "trailingEps": 3.77, "forwardEps": 6.46, "lastSplitFactor": "2:1", "lastSplitDate": 1075161600, "enterpriseToRevenue": 0.503, "enterpriseToEbitda": 8.037, "52WeekChange": -0.31899387, "SandP52WeekChange": 0.08089435, "lastDividendValue": 0.5, "lastDividendDate": 1736121600, "quoteType": "EQUITY", "currentPrice": 76.62, "targetHighPrice": 126.0, "targetLowPrice": 65.0, "targetMeanPrice": 91.16667, "targetMedianPrice": 91.0, "recommendationMean": 2.76471, "recommendationKey": "hold", "numberOfAnalystOpinions": 12, "totalCash": 373819008, "totalCashPerShare": 7.026, "ebitda": 594494016, "totalDebt": 1073815040, "quickRatio": 0.697, "currentRatio": 1.712, "totalRevenue": 9496170496, "debtToEquity": 27.161, "revenuePerShare": 178.702, "returnOnAssets": 0.02861, "returnOnEquity": 0.05093, "grossProfits": 1349821952, "freeCashflow": 552167616, "operatingCashflow": 651329984, "revenueGrowth": -0.086, "grossMargins": 0.14214, "ebitdaMargins": 0.0626, "operatingMargins": 0.00482, "financialCurrency": "USD", "symbol": "THO", "language": "en-US", "region": "US", "typeDisp": "Equity", "triggerable": true, "customPriceAlertConfidence": "HIGH", "cryptoTradeable": false, "marketState": "PRE", "regularMarketChangePercent": 1.06847, "regularMarketPrice": 76.62, "corporateActions": [{"header": "Dividend", "message": "THO announced a cash dividend of 0.50 with an ex-date of Apr. 8, 2025", "meta": {"eventType": "DIVIDEND", "dateEpochMs": 1744084800000, "amount": "0.50"}}], "preMarketTime": 1743598878, "regularMarketTime": 1743537601, "exchange": "NYQ", "messageBoardId": "finmb_308299", "exchangeTimezoneName": "America/New_York", "exchangeTimezoneShortName": "EDT", "gmtOffSetMilliseconds": -14400000, "market": "us_market", "esgPopulated": false, "preMarketChange": -0.6300049, "preMarketChangePercent": -0.82224596, "preMarketPrice": 75.99, "regularMarketChange": 0.810005, "regularMarketDayRange": "74.95 - 77.1559", "fullExchangeName": "NYSE", "averageDailyVolume3Month": 812288, "fiftyTwoWeekLowChange": 1.6700058, "fiftyTwoWeekLowChangePercent": 0.0222816, "fiftyTwoWeekRange": "74.95 - 118.85", "fiftyTwoWeekHighChange": -42.229996, "fiftyTwoWeekHighChangePercent": -0.3553218, "fiftyTwoWeekChangePercent": -31.899387, "dividendDate": 1745280000, "earningsTimestamp": 1741174200, "earningsTimestampStart": 1748953800, "earningsTimestampEnd": 1749472200, "isEarningsDateEstimate": true, "epsTrailingTwelveMonths": 3.77, "epsForward": 6.46, "epsCurrentYear": 3.58246, "priceEpsCurrentYear": 21.387539, "fiftyDayAverageChange": -16.379997, "fiftyDayAverageChangePercent": -0.176129, "twoHundredDayAverageChange": -23.68425, "twoHundredDayAverageChangePercent": -0.23612408, "sourceInterval": 15, "exchangeDataDelayedBy": 0, "averageAnalystRating": "2.8 - Hold", "hasPrePostMarketData": true, "firstTradeDateMilliseconds": 442593000000, "shortName": "Thor Industries, Inc.", "longName": "THOR Industries, Inc.", "displayName": "THOR Industries", "trailingPegRatio": 0.651}