{"address1": "100 First Stamford Place", "address2": "Suite 700", "city": "Stamford", "state": "CT", "zip": "06902", "country": "United States", "phone": "203 622 3131", "fax": "203 622 6080", "website": "https://www.unitedrentals.com", "industry": "Rental & Leasing Services", "industryKey": "rental-leasing-services", "industryDisp": "Rental & Leasing Services", "sector": "Industrials", "sectorKey": "industrials", "sectorDisp": "Industrials", "longBusinessSummary": "United Rentals, Inc., through its subsidiaries, operates as an equipment rental company. It operates in two segments, General Rentals and Specialty. The General Rentals segment rents general construction and industrial equipment includes backhoes, skid-steer loaders, forklifts, earthmoving equipment, and material handling equipment; aerial work platforms, such as boom and scissor lifts; and general tools and light equipment comprising pressure washers, water pumps, and power tools for construction and industrial companies, manufacturers, utilities, municipalities, homeowners, and government entities. The specialty segment rents trench safety equipment consists of trench shields, aluminum hydraulic shoring systems, slide rails, crossing plates, construction lasers, and line testing equipment for underground work; power and heating, ventilating, and air conditioning equipment, such as portable diesel generators, electrical distribution equipment, and temperature control equipment; fluid solutions equipment for fluid containment, transfer, and treatment; surface protection mats; and mobile storage equipment and modular office space. This segment serves construction companies involved in infrastructure projects, and municipalities and industrial companies. It also sells aerial lifts, reach forklifts, telehandlers, compressors, and generators; construction consumables, tools, small equipment, and safety supplies; and parts for equipment that is owned by its customers, as well as provides repair and maintenance services. The company sells used equipment through its sales force, brokers, website, at auctions, and directly to manufacturers. The company operates in the United States, Canada, Europe, Australia, and New Zealand. United Rentals, Inc. was incorporated in 1997 and is headquartered in Stamford, Connecticut.", "fullTimeEmployees": 27900, "companyOfficers": [{"maxAge": 1, "name": "Mr. Matthew J. Flannery", "age": 59, "title": "President, CEO & Director", "yearBorn": 1965, "fiscalYear": 2024, "totalPay": 3045955, "exercisedValue": 0, "unexercisedValue": 0}, {"maxAge": 1, "name": "Mr. William Edward Grace", "age": 52, "title": "Executive VP & CFO", "yearBorn": 1972, "fiscalYear": 2024, "totalPay": 1321198, "exercisedValue": 0, "unexercisedValue": 0}, {"maxAge": 1, "name": "Mr. Michael D. Durand", "age": 50, "title": "Executive VP & COO", "yearBorn": 1974, "fiscalYear": 2024, "totalPay": 1254766, "exercisedValue": 0, "unexercisedValue": 0}, {"maxAge": 1, "name": "Mr. Craig Adam Pintoff J.D.", "age": 54, "title": "Executive VP & Chief Administrative Officer", "yearBorn": 1970, "fiscalYear": 2024, "totalPay": 1394770, "exercisedValue": 0, "unexercisedValue": 0}, {"maxAge": 1, "name": "Ms. Joli L. Gross J.D.", "age": 53, "title": "Senior VP, Corporate Secretary and Chief Legal & Sustainability Officer", "yearBorn": 1971, "fiscalYear": 2024, "totalPay": 1152119, "exercisedValue": 0, "unexercisedValue": 0}, {"maxAge": 1, "name": "Mr. Andrew B. Limoges", "age": 42, "title": "VP, Controller & Principal Accounting Officer", "yearBorn": 1982, "fiscalYear": 2024, "totalPay": 729806, "exercisedValue": 0, "unexercisedValue": 0}, {"maxAge": 1, "name": "Mr. Anthony S. Leopold", "age": 47, "title": "Senior VP and Chief Technology & Strategy Officer", "yearBorn": 1977, "fiscalYear": 2024, "exercisedValue": 0, "unexercisedValue": 0}, {"maxAge": 1, "name": "Mr. Daniel T. Higgins", "title": "VP & Chief Information Officer", "fiscalYear": 2024, "exercisedValue": 0, "unexercisedValue": 0}, {"maxAge": 1, "name": "Ms. Elizabeth Carolyn Grenfell", "title": "Vice President of Investor Relations", "fiscalYear": 2024, "exercisedValue": 0, "unexercisedValue": 0}, {"maxAge": 1, "name": "Mr. Robert N. Halsey", "title": "Vice President of Marketing", "fiscalYear": 2024, "exercisedValue": 0, "unexercisedValue": 0}], "auditRisk": 5, "boardRisk": 4, "compensationRisk": 2, "shareHolderRightsRisk": 2, "overallRisk": 1, "governanceEpochDate": 1743465600, "compensationAsOfEpochDate": 1735603200, "irWebsite": "http://www.unitedrentals.com/en/our-company/investor-relations", "executiveTeam": [], "maxAge": 86400, "priceHint": 2, "previousClose": 626.7, "open": 620.63, "dayLow": 612.865, "dayHigh": 632.85, "regularMarketPreviousClose": 626.7, "regularMarketOpen": 620.63, "regularMarketDayLow": 612.865, "regularMarketDayHigh": 632.85, "dividendRate": 7.16, "dividendYield": 1.13, "exDividendDate": 1739318400, "payoutRatio": 0.1685, "beta": 1.767, "trailingPE": 16.338934, "forwardPE": 13.486769, "volume": 459548, "regularMarketVolume": 459548, "averageVolume": 698171, "averageVolume10days": 578430, "averageDailyVolume10Day": 578430, "bid": 590.0, "ask": 635.0, "bidSize": 8, "askSize": 12, "marketCap": 41289232384, "fiftyTwoWeekLow": 585.27, "fiftyTwoWeekHigh": 896.98, "priceToSalesTrailing12Months": 2.6907287, "fiftyDayAverage": 681.8816, "twoHundredDayAverage": 734.5295, "trailingAnnualDividendRate": 6.52, "trailingAnnualDividendYield": 0.010403702, "currency": "USD", "tradeable": false, "enterpriseValue": 55605432320, "profitMargins": 0.16781001, "floatShares": 64953787, "sharesOutstanding": 65332100, "sharesShort": 1742441, "sharesShortPriorMonth": 1676123, "sharesShortPreviousMonthDate": 1739491200, "dateShortInterest": 1741910400, "sharesPercentSharesOut": 0.026700001, "heldPercentInsiders": 0.00514, "heldPercentInstitutions": 0.93992996, "shortRatio": 2.1, "shortPercentOfFloat": 0.030299999, "impliedSharesOutstanding": 65431100, "bookValue": 132.025, "priceToBook": 4.7868967, "lastFiscalYearEnd": 1735603200, "nextFiscalYearEnd": 1767139200, "mostRecentQuarter": 1735603200, "earningsQuarterlyGrowth": 0.015, "netIncomeToCommon": 2575000064, "trailingEps": 38.68, "forwardEps": 46.86, "enterpriseToRevenue": 3.624, "enterpriseToEbitda": 12.173, "52WeekChange": -0.10500753, "SandP52WeekChange": 0.08089435, "lastDividendValue": 1.79, "lastDividendDate": 1739318400, "quoteType": "EQUITY", "currentPrice": 631.99, "targetHighPrice": 1238.0, "targetLowPrice": 535.0, "targetMeanPrice": 788.9537, "targetMedianPrice": 765.0, "recommendationMean": 2.3913, "recommendationKey": "buy", "numberOfAnalystOpinions": 19, "totalCash": 457000000, "totalCashPerShare": 6.998, "ebitda": 4568000000, "totalDebt": 14789000192, "quickRatio": 0.875, "currentRatio": 0.978, "totalRevenue": 15345000448, "debtToEquity": 171.526, "revenuePerShare": 231.291, "returnOnAssets": 0.09607001, "returnOnEquity": 0.30743, "grossProfits": 6213000192, "freeCashflow": 2280000000, "operatingCashflow": 4545999872, "earningsGrowth": 0.045, "revenueGrowth": 0.098, "grossMargins": 0.40488997, "ebitdaMargins": 0.29769, "operatingMargins": 0.26935, "financialCurrency": "USD", "symbol": "URI", "language": "en-US", "region": "US", "typeDisp": "Equity", "quoteSourceName": "Nasdaq Real Time Price", "triggerable": true, "customPriceAlertConfidence": "HIGH", "regularMarketChange": 5.28998, "regularMarketDayRange": "612.865 - 632.85", "fullExchangeName": "NYSE", "averageDailyVolume3Month": 698171, "fiftyTwoWeekLowChange": 46.71997, "fiftyTwoWeekLowChangePercent": 0.079826355, "fiftyTwoWeekRange": "585.27 - 896.98", "fiftyTwoWeekHighChange": -264.99, "fiftyTwoWeekHighChangePercent": -0.29542464, "fiftyTwoWeekChangePercent": -10.500753, "dividendDate": 1740528000, "earningsTimestamp": 1738185300, "earningsTimestampStart": 1745319540, "earningsTimestampEnd": 1745841600, "earningsCallTimestampStart": 1738243800, "earningsCallTimestampEnd": 1738243800, "isEarningsDateEstimate": true, "epsTrailingTwelveMonths": 38.68, "epsForward": 46.86, "epsCurrentYear": 44.23936, "priceEpsCurrentYear": 14.285694, "fiftyDayAverageChange": -49.8916, "fiftyDayAverageChangePercent": -0.07316755, "twoHundredDayAverageChange": -102.53949, "twoHundredDayAverageChangePercent": -0.13959888, "sourceInterval": 15, "exchangeDataDelayedBy": 0, "averageAnalystRating": "2.4 - Buy", "cryptoTradeable": false, "marketState": "PRE", "regularMarketChangePercent": 0.8441, "regularMarketPrice": 631.99, "corporateActions": [], "preMarketTime": 1743599679, "regularMarketTime": 1743537601, "exchange": "NYQ", "messageBoardId": "finmb_36005", "exchangeTimezoneName": "America/New_York", "exchangeTimezoneShortName": "EDT", "gmtOffSetMilliseconds": -14400000, "market": "us_market", "esgPopulated": false, "shortName": "United Rentals, Inc.", "longName": "United Rentals, Inc.", "hasPrePostMarketData": true, "firstTradeDateMilliseconds": 882455400000, "preMarketChange": -10.580017, "preMarketChangePercent": -1.6740799, "preMarketPrice": 621.41, "displayName": "United Rentals", "trailingPegRatio": 1.2734}