{"address1": "202 6th Street", "address2": "Suite 400", "city": "Castle Rock", "state": "CO", "zip": "80104", "country": "United States", "phone": "303 895 3002", "website": "https://wherefoodcomesfrom.com", "industry": "Specialty Business Services", "industryKey": "specialty-business-services", "industryDisp": "Specialty Business Services", "sector": "Industrials", "sectorKey": "industrials", "sectorDisp": "Industrials", "longBusinessSummary": "Where Food Comes From, Inc., together with its subsidiaries, operates as a third-party food verification company in the United States. It operates through Verification and Certification, and Professional Services segments. The company conducts on-site and desk audits to verify that claims being made about livestock, food, other specialty crops, and agricultural and aquaculture products are accurate, as well as offers Where Food Comes from Source Verified retail and restaurant labeling program, which connects consumers directly to the source of the food they purchase through product labeling, and web-based information sharing and education. It also provides professional services and technology solutions; verification solutions; and consulting services, as well as sells hardware. It serves beef and pork packers, organic producers and processors, and specialty retail chains. The company was formerly known as Integrated Management Information, Inc. and changed its name to Where Food Comes From, Inc. in December 2012. Where Food Comes From, Inc. was founded in 1996 and is based in Castle Rock, Colorado.", "fullTimeEmployees": 93, "companyOfficers": [{"maxAge": 1, "name": "Mr. John K. Saunders", "age": 52, "title": "Co-Founder, CEO & Executive Chairman", "yearBorn": 1972, "fiscalYear": 2024, "totalPay": 531205, "exercisedValue": 0, "unexercisedValue": 10660}, {"maxAge": 1, "name": "Ms. Leann  Saunders", "age": 53, "title": "Co-Founder, President, COO & Director", "yearBorn": 1971, "fiscalYear": 2024, "totalPay": 531205, "exercisedValue": 0, "unexercisedValue": 10660}, {"maxAge": 1, "name": "Ms. Dannette D. Boyd Henning", "age": 54, "title": "CFO & Corporate Secretary", "yearBorn": 1970, "fiscalYear": 2024, "totalPay": 414732, "exercisedValue": 0, "unexercisedValue": 10660}, {"maxAge": 1, "name": "Sara  Simpson", "title": "Accounting Manager", "fiscalYear": 2024, "exercisedValue": 0, "unexercisedValue": 0}, {"maxAge": 1, "name": "Mr. Jason  Franco", "title": "Chief Technology Officer", "fiscalYear": 2024, "exercisedValue": 0, "unexercisedValue": 0}, {"maxAge": 1, "name": "Mr. Jay  Pfeiffer", "title": "Manager of Investor Relations", "fiscalYear": 2024, "exercisedValue": 0, "unexercisedValue": 0}, {"maxAge": 1, "name": "Mr. James  Riva", "title": "Compliance Manager", "fiscalYear": 2024, "exercisedValue": 0, "unexercisedValue": 0}, {"maxAge": 1, "name": "CJ  Scott", "title": "Marketing & Communications Manager", "fiscalYear": 2024, "exercisedValue": 0, "unexercisedValue": 0}, {"maxAge": 1, "name": "Mr. Doug  Stanton", "title": "Senior VP of Sales & Business Development", "fiscalYear": 2024, "exercisedValue": 0, "unexercisedValue": 0}, {"maxAge": 1, "name": "Sarah  Haskins", "title": "HR Director", "fiscalYear": 2024, "exercisedValue": 0, "unexercisedValue": 0}], "compensationAsOfEpochDate": 1735603200, "irWebsite": "http://www.imiglobal.com/Investors.html", "executiveTeam": [], "maxAge": 86400, "priceHint": 2, "previousClose": 11.07, "open": 11.3104, "dayLow": 11.3104, "dayHigh": 11.3104, "regularMarketPreviousClose": 11.07, "regularMarketOpen": 11.3104, "regularMarketDayLow": 11.3104, "regularMarketDayHigh": 11.3104, "exDividendDate": 1627257600, "payoutRatio": 0.0, "beta": 0.406, "trailingPE": 28.276, "forwardPE": 23.082449, "volume": 340, "regularMarketVolume": 340, "averageVolume": 4183, "averageVolume10days": 6800, "averageDailyVolume10Day": 6800, "bid": 0.0, "ask": 0.0, "bidSize": 0, "askSize": 0, "marketCap": 59188908, "fiftyTwoWeekLow": 9.76, "fiftyTwoWeekHigh": 13.5, "priceToSalesTrailing12Months": 2.2989554, "fiftyDayAverage": 11.892, "twoHundredDayAverage": 11.6242, "trailingAnnualDividendRate": 0.0, "trailingAnnualDividendYield": 0.0, "currency": "USD", "tradeable": false, "enterpriseValue": 59722928, "profitMargins": 0.08234, "floatShares": 1925064, "sharesOutstanding": 5233140, "sharesShort": 10979, "sharesShortPriorMonth": 19535, "sharesShortPreviousMonthDate": 1739491200, "dateShortInterest": 1741910400, "sharesPercentSharesOut": 0.0021, "heldPercentInsiders": 0.50472, "heldPercentInstitutions": 0.24341999, "shortRatio": 2.52, "shortPercentOfFloat": 0.0043, "impliedSharesOutstanding": 5233140, "bookValue": 1.895, "priceToBook": 5.968549, "lastFiscalYearEnd": 1735603200, "nextFiscalYearEnd": 1767139200, "mostRecentQuarter": 1735603200, "earningsQuarterlyGrowth": 0.238, "netIncomeToCommon": 2120000, "trailingEps": 0.4, "forwardEps": 0.49, "lastSplitFactor": "1:4", "lastSplitDate": 1607299200, "enterpriseToRevenue": 2.32, "enterpriseToEbitda": 20.926, "52WeekChange": 0.119802, "SandP52WeekChange": 0.08089435, "lastDividendValue": 0.15, "lastDividendDate": 1627257600, "quoteType": "EQUITY", "currentPrice": 11.3104, "recommendationKey": "none", "totalCash": 2012000, "totalCashPerShare": 0.384, "ebitda": 2854000, "totalDebt": 2546000, "quickRatio": 1.207, "currentRatio": 1.744, "totalRevenue": 25746000, "debtToEquity": 25.632, "revenuePerShare": 4.841, "returnOnAssets": 0.08732, "returnOnEquity": 0.20432, "grossProfits": 10562000, "freeCashflow": 2097875, "operatingCashflow": 2730000, "earningsGrowth": 0.25, "revenueGrowth": -0.01, "grossMargins": 0.41024, "ebitdaMargins": 0.11085, "operatingMargins": 0.11333, "financialCurrency": "USD", "symbol": "WFCF", "language": "en-US", "region": "US", "typeDisp": "Equity", "quoteSourceName": "Nasdaq Real Time Price", "triggerable": true, "customPriceAlertConfidence": "HIGH", "regularMarketChangePercent": 2.1716378, "regularMarketPrice": 11.3104, "marketState": "PRE", "shortName": "Where Food Comes From, Inc.", "longName": "Where Food Comes From, Inc.", "fiftyDayAverageChange": -0.5816002, "fiftyDayAverageChangePercent": -0.048906844, "twoHundredDayAverageChange": -0.31379986, "twoHundredDayAverageChangePercent": -0.026995394, "sourceInterval": 15, "exchangeDataDelayedBy": 0, "ipoExpectedDate": "2021-04-12", "cryptoTradeable": false, "hasPrePostMarketData": true, "firstTradeDateMilliseconds": 1163601000000, "regularMarketChange": 0.24040031, "regularMarketDayRange": "11.3104 - 11.3104", "fullExchangeName": "NasdaqCM", "averageDailyVolume3Month": 4183, "fiftyTwoWeekLowChange": 1.5503998, "fiftyTwoWeekLowChangePercent": 0.15885243, "fiftyTwoWeekRange": "9.76 - 13.5", "fiftyTwoWeekHighChange": -2.1896, "fiftyTwoWeekHighChangePercent": -0.1621926, "fiftyTwoWeekChangePercent": 11.9802, "dividendDate": 1629072000, "earningsTimestamp": 1740058200, "earningsTimestampStart": 1746010740, "earningsTimestampEnd": 1746446400, "earningsCallTimestampStart": 1740070800, "earningsCallTimestampEnd": 1740070800, "isEarningsDateEstimate": true, "epsTrailingTwelveMonths": 0.4, "epsForward": 0.49, "corporateActions": [], "regularMarketTime": 1743537600, "exchange": "NCM", "messageBoardId": "finmb_26971219", "exchangeTimezoneName": "America/New_York", "exchangeTimezoneShortName": "EDT", "gmtOffSetMilliseconds": -14400000, "market": "us_market", "esgPopulated": false, "displayName": "Where Food Comes From", "trailingPegRatio": null}